rcs_chatbot/__init__.py
rcs_chatbot-0.0.6.dist-info/LICENSE
rcs_chatbot-0.0.6.dist-info/METADATA
rcs_chatbot-0.0.6.dist-info/WHEEL
rcs_chatbot-0.0.6.dist-info/top_level.txt
rcs_chatbot-0.0.6.dist-info/RECORD
