Metadata-Version: 2.1
Name: rcs-chatbot
Version: 0.0.6
Summary: Python SDK for RCS MaaP chatbot
Home-page: https://github.com/pvangool/py-rcs-chatbot
Author: Paul van Gool
Author-email: pvangool@gmail.com
License: UNKNOWN
Platform: UNKNOWN
Classifier: Programming Language :: Python :: 3
Classifier: License :: OSI Approved :: MIT License
Classifier: Operating System :: OS Independent
